[{"inputs":[],"stateMutability":"nonpayable","type":"constructor"},{"outputs":[{"name":"direccion","internalType":"address","type":"address"},{"name":"usuario","internalType":"string","type":"string"},{"name":"clave","internalType":"bytes32","type":"bytes32"}],"inputs":[{"name":"","internalType":"uint256","type":"uint256"}],"name":"acl_array","stateMutability":"view","type":"function"},{"outputs":[],"inputs":[],"name":"activar","stateMutability":"nonpayable","type":"function"},{"outputs":[],"inputs":[{"name":"clave","internalType":"bytes","type":"bytes"}],"name":"actualizar_administrador_clave","stateMutability":"nonpayable","type":"function"},{"outputs":[],"inputs":[{"components":[{"name":"direccion","internalType":"address","type":"address"},{"name":"usuario","internalType":"string","type":"string"},{"name":"clave","internalType":"bytes32","type":"bytes32"},{"name":"permisos_array","internalType":"bytes32[]","type":"bytes32[]"}],"name":"acl","internalType":"struct acls","type":"tuple"}],"name":"actualizar_administrador_pero_no_clave","stateMutability":"nonpayable","type":"function"},{"outputs":[],"inputs":[{"name":"direccion","internalType":"address","type":"address"}],"name":"borrar_administrador","stateMutability":"nonpayable","type":"function"},{"outputs":[],"inputs":[{"name":"usuario","internalType":"string","type":"string"},{"name":"nueva_direccion","internalType":"address","type":"address"}],"name":"cambiar_direccion","stateMutability":"nonpayable","type":"function"},{"outputs":[{"name":"","internalType":"bool","type":"bool"}],"inputs":[{"name":"direccion","internalType":"address","type":"address"},{"name":"clave","internalType":"bytes","type":"bytes"}],"name":"comprobar_clave","stateMutability":"view","type":"function"},{"outputs":[],"inputs":[{"name":"direccion","internalType":"address","type":"address"},{"name":"usuario","internalType":"string","type":"string"},{"name":"clave","internalType":"bytes","type":"bytes"},{"name":"permisos_array","internalType":"bytes32[]","type":"bytes32[]"}],"name":"crear_administrador","stateMutability":"nonpayable","type":"function"},{"outputs":[{"name":"","internalType":"enum estados","type":"uint8"}],"inputs":[],"name":"estado","stateMutability":"view","type":"function"},{"outputs":[],"inputs":[],"name":"inactivar","stateMutability":"nonpayable","type":"function"},{"outputs":[{"components":[{"name":"direccion","internalType":"address","type":"address"},{"name":"usuario","internalType":"string","type":"string"},{"name":"clave","internalType":"bytes32","type":"bytes32"},{"name":"permisos_array","internalType":"bytes32[]","type":"bytes32[]"}],"name":"","internalType":"struct acls","type":"tuple"}],"inputs":[{"name":"direccion","internalType":"address","type":"address"}],"name":"leer_administrador","stateMutability":"view","type":"function"},{"outputs":[{"name":"","internalType":"int256","type":"int256"}],"inputs":[{"name":"direccion","internalType":"address","type":"address"}],"name":"leer_administrador_pos","stateMutability":"view","type":"function"},{"outputs":[],"inputs":[],"name":"limitar","stateMutability":"nonpayable","type":"function"},{"outputs":[{"name":"","internalType":"bool","type":"bool"}],"inputs":[{"name":"direccion","internalType":"address","type":"address"}],"name":"ser_administrador","stateMutability":"view","type":"function"},{"outputs":[{"name":"","internalType":"bool","type":"bool"}],"inputs":[{"name":"direccion","internalType":"address","type":"address"},{"name":"permiso_necesario","internalType":"bytes32","type":"bytes32"}],"name":"ser_administrador_con_permiso","stateMutability":"view","type":"function"}]