[{"outputs":[{"name":"","internalType":"string","type":"string"}],"inputs":[{"name":"bytex32","internalType":"bytes32","type":"bytes32"}],"name":"convertir_bytes32_a_string","stateMutability":"pure","type":"function"},{"outputs":[{"name":"","internalType":"bool","type":"bool"}],"inputs":[{"name":"bytex_1","internalType":"bytes","type":"bytes"},{"name":"bytex_2","internalType":"bytes","type":"bytes"}],"name":"ser_igual_bytes","stateMutability":"pure","type":"function"},{"outputs":[{"name":"","internalType":"bool","type":"bool"}],"inputs":[{"name":"tex_1","internalType":"string","type":"string"},{"name":"tex_2","internalType":"string","type":"string"}],"name":"ser_igual_string","stateMutability":"pure","type":"function"}]